beacontools/__init__.py
beacontools/const.py
beacontools/device_filters.py
beacontools/parser.py
beacontools/scanner.py
beacontools/utils.py
beacontools/backend/__init__.py
beacontools/backend/freebsd.py
beacontools/backend/linux.py
beacontools/packet_types/__init__.py
beacontools/packet_types/controlj.py
beacontools/packet_types/eddystone.py
beacontools/packet_types/estimote.py
beacontools/packet_types/exposure_notification.py
beacontools/packet_types/ibeacon.py
beacontools/structs/__init__.py
beacontools/structs/common.py
beacontools/structs/controlj.py
beacontools/structs/eddystone.py
beacontools/structs/estimote.py
beacontools/structs/exposure_notification.py
beacontools/structs/ibeacon.py
beacontools-2.1.0.dist-info/LICENSE.txt
beacontools-2.1.0.dist-info/METADATA
beacontools-2.1.0.dist-info/WHEEL
beacontools-2.1.0.dist-info/top_level.txt
beacontools-2.1.0.dist-info/RECORD
