Metadata-Version: 2.1
Name: beacontools
Version: 2.1.0
Summary: A Python library for working with various types of Bluetooth LE Beacons.
Home-page: https://github.com/citruz/beacontools
Author: Felix Seele
Author-email: fseele@gmail.com
License: MIT
Keywords: beacons ibeacon eddystone bluetooth low energy ble
Platform: UNKNOWN
Classifier: Development Status :: 5 - Production/Stable
Classifier: Intended Audience :: Developers
Classifier: Topic :: Software Development :: Libraries
Classifier: License :: OSI Approved :: MIT License
Classifier: Programming Language :: Python :: 3
Classifier: Programming Language :: Python :: 3.5
Classifier: Programming Language :: Python :: 3.6
Classifier: Programming Language :: Python :: 3.7
Requires-Dist: construct (<2.11,>=2.9.52)
Requires-Dist: ahocorapy (==1.6.1)
Provides-Extra: dev
Requires-Dist: check-manifest ; extra == 'dev'
Provides-Extra: scan
Provides-Extra: test
Requires-Dist: coveralls (~=2.1) ; extra == 'test'
Requires-Dist: pytest (~=6.0) ; extra == 'test'
Requires-Dist: pytest-cov (~=2.10) ; extra == 'test'
Requires-Dist: mock (~=4.0) ; extra == 'test'
Requires-Dist: check-manifest ; extra == 'test'
Requires-Dist: pylint ; extra == 'test'
Requires-Dist: readme-renderer ; extra == 'test'
Requires-Dist: docutils ; extra == 'test'
